problem4/problem4.v
module problem4(
    input i_rst,
    input i_clk,
    output reg [15:0] o_p
);

    always @(posedge i_clk) begin
        if (i_rst) begin
            o_p <= 16'h0000;
        end else begin
            o_p <= 16'h0001 + o_p;
        end
    end

endmodule

problem4/problem4_tb.v
module problem4_tb;
    reg           i_clk     = 0;
    reg           i_rst     = 0;
    wire  [15:0]  o_p;

    initial begin
        $dumpfile("wave.vcd");
        $dumpvars(0, DUT);
    end

    problem4 DUT(
        .i_clk  (i_clk  ),
        .i_rst  (i_rst  ),
        .o_p    (o_p    )
    );

    always #1 begin    
        i_clk <= ~i_clk;
    end

    initial begin
        i_rst   = 1'b1;
        #10
        i_rst   = 1'b0;
        #100
        $finish;
    end
endmodule

problem4/wave.vcd
$date
	Sun Sep 17 20:30:52 2023
$end
$version
	Icarus Verilog
$end
$timescale
	1s
$end
$scope module problem4_tb $end
$scope module DUT $end
$var wire 1 ! i_clk $end
$var wire 1 " i_rst $end
$var reg 16 # o_p [15:0] $end
$upscope $end
$upscope $end
$enddefinitions $end
$comment Show the parameter values. $end
$dumpall
$end
#0
$dumpvars
bx #
1"
0!
$end
#1
b0 #
1!
#2
0!
#3
1!
#4
0!
#5
1!
#6
0!
#7
1!
#8
0!
#9
1!
#10
0!
0"
#11
b1 #
1!
#12
0!
#13
b10 #
1!
#14
0!
#15
b11 #
1!
#16
0!
#17
b100 #
1!
#18
0!
#19
b101 #
1!
#20
0!
#21
b110 #
1!
#22
0!
#23
b111 #
1!
#24
0!
#25
b1000 #
1!
#26
0!
#27
b1001 #
1!
#28
0!
#29
b1010 #
1!
#30
0!
#31
b1011 #
1!
#32
0!
#33
b1100 #
1!
#34
0!
#35
b1101 #
1!
#36
0!
#37
b1110 #
1!
#38
0!
#39
b1111 #
1!
#40
0!
#41
b10000 #
1!
#42
0!
#43
b10001 #
1!
#44
0!
#45
b10010 #
1!
#46
0!
#47
b10011 #
1!
#48
0!
#49
b10100 #
1!
#50
0!
#51
b10101 #
1!
#52
0!
#53
b10110 #
1!
#54
0!
#55
b10111 #
1!
#56
0!
#57
b11000 #
1!
#58
0!
#59
b11001 #
1!
#60
0!
#61
b11010 #
1!
#62
0!
#63
b11011 #
1!
#64
0!
#65
b11100 #
1!
#66
0!
#67
b11101 #
1!
#68
0!
#69
b11110 #
1!
#70
0!
#71
b11111 #
1!
#72
0!
#73
b100000 #
1!
#74
0!
#75
b100001 #
1!
#76
0!
#77
b100010 #
1!
#78
0!
#79
b100011 #
1!
#80
0!
#81
b100100 #
1!
#82
0!
#83
b100101 #
1!
#84
0!
#85
b100110 #
1!
#86
0!
#87
b100111 #
1!
#88
0!
#89
b101000 #
1!
#90
0!
#91
b101001 #
1!
#92
0!
#93
b101010 #
1!
#94
0!
#95
b101011 #
1!
#96
0!
#97
b101100 #
1!
#98
0!
#99
b101101 #
1!
#100
0!
#101
b101110 #
1!
#102
0!
#103
b101111 #
1!
#104
0!
#105
b110000 #
1!
#106
0!
#107
b110001 #
1!
#108
0!
#109
b110010 #
1!
